huaweicloudsdkrds/__init__.py
huaweicloudsdkrds/v3/__init__.py
huaweicloudsdkrds/v3/rds_async_client.py
huaweicloudsdkrds/v3/rds_client.py
huaweicloudsdkrds/v3/model/__init__.py
huaweicloudsdkrds/v3/model/ad_domain_info.py
huaweicloudsdkrds/v3/model/add_copy_database_request_body.py
huaweicloudsdkrds/v3/model/add_log_config_response_body.py
huaweicloudsdkrds/v3/model/add_log_configs.py
huaweicloudsdkrds/v3/model/add_msdtc_request_body.py
huaweicloudsdkrds/v3/model/add_postgresql_hba_conf_request.py
huaweicloudsdkrds/v3/model/add_postgresql_hba_conf_response.py
huaweicloudsdkrds/v3/model/agreement.py
huaweicloudsdkrds/v3/model/allow_db_privilege_request.py
huaweicloudsdkrds/v3/model/allow_db_privilege_response.py
huaweicloudsdkrds/v3/model/allow_db_user_privilege_request.py
huaweicloudsdkrds/v3/model/allow_db_user_privilege_response.py
huaweicloudsdkrds/v3/model/allow_sqlserver_db_user_privilege_request.py
huaweicloudsdkrds/v3/model/allow_sqlserver_db_user_privilege_response.py
huaweicloudsdkrds/v3/model/api_version.py
huaweicloudsdkrds/v3/model/applicable_instance_info.py
huaweicloudsdkrds/v3/model/apply_configuration_async_request.py
huaweicloudsdkrds/v3/model/apply_configuration_async_response.py
huaweicloudsdkrds/v3/model/apply_configuration_request.py
huaweicloudsdkrds/v3/model/apply_configuration_response_apply_results.py
huaweicloudsdkrds/v3/model/apply_history_info.py
huaweicloudsdkrds/v3/model/article_properties_request.py
huaweicloudsdkrds/v3/model/article_properties_response.py
huaweicloudsdkrds/v3/model/attach_eip_request.py
huaweicloudsdkrds/v3/model/attach_eip_response.py
huaweicloudsdkrds/v3/model/auditlog.py
huaweicloudsdkrds/v3/model/auto_ces_alarm_info.py
huaweicloudsdkrds/v3/model/auto_enlarge_strategy_for_console_api.py
huaweicloudsdkrds/v3/model/available_zone.py
huaweicloudsdkrds/v3/model/backup_database.py
huaweicloudsdkrds/v3/model/backup_datastore.py
huaweicloudsdkrds/v3/model/backup_for_list.py
huaweicloudsdkrds/v3/model/backup_info.py
huaweicloudsdkrds-3.1.184.dist-info/METADATA
huaweicloudsdkrds-3.1.184.dist-info/WHEEL
huaweicloudsdkrds-3.1.184.dist-info/licenses/LICENSE
huaweicloudsdkrds-3.1.184.dist-info/RECORD
